dalpy/__init__.py
dalpy/arrays.py
dalpy/factory_utils.py
dalpy/graphs.py
dalpy/hashing.py
dalpy/heaps.py
dalpy/linked_lists.py
dalpy/misc_utils.py
dalpy/queues.py
dalpy/sets.py
dalpy/stacks.py
dalpy/test_utils.py
dalpy/trees.py
dalpy-1.0.2.dist-info/LICENSE
dalpy-1.0.2.dist-info/METADATA
dalpy-1.0.2.dist-info/WHEEL
dalpy-1.0.2.dist-info/top_level.txt
dalpy-1.0.2.dist-info/RECORD
