Metadata-Version: 2.1
Name: dalpy
Version: 1.0.2
Summary: A Python package for learning data structures and algorithms.
Home-page: https://github.com/DALPy-Developers/DALPy
Author: Eitan Joseph and Chami Lamelas
Author-email: eitanjoseph@brandeis.edu, slamelas@brandeis.edu
Project-URL: Source Code, https://github.com/DALPy-Developers/DALPy
Project-URL: Documentation, https://dalpy-developers.github.io/DALPy/
Project-URL: Bug Tracker, https://github.com/DALPy-Developers/DALPy/issues
Project-URL: Sample Usage, https://github.com/DALPy-Developers/DALPy-Sample-Problems
Project-URL: Article, https://www.thejustice.org/article/2022/04/a-software-called-dalpy-was-created-by-two-undergraduate-students-and-will-assist-teaching-testing-and-grading-at-the-university-brandeis
Classifier: Programming Language :: Python :: 3
Classifier: License :: OSI Approved :: MIT License
Classifier: Operating System :: OS Independent
Requires-Python: >=3.6
License-File: LICENSE
